<?xml version="1.0" encoding="utf-8"?>
<SoundBanksInfo Platform="Mac" BasePlatform="Mac" SchemaVersion="11" SoundbankVersion="120">
	<RootPaths>
		<ProjectRoot>D:\Github\CS190-Project2\CS190_Project2\CS190_Project2_WwiseProject\</ProjectRoot>
		<SourceFilesRoot>D:\Github\CS190-Project2\CS190_Project2\CS190_Project2_WwiseProject\.cache\Mac\</SourceFilesRoot>
		<SoundBanksRoot>D:\Github\CS190-Project2\CS190_Project2\CS190_Project2_WwiseProject\GeneratedSoundBanks\Mac\</SoundBanksRoot>
		<ExternalSourcesInputFile></ExternalSourcesInputFile>
		<ExternalSourcesOutputRoot>D:\Github\CS190-Project2\CS190_Project2\CS190_Project2_WwiseProject\GeneratedSoundBanks\Mac\</ExternalSourcesOutputRoot>
	</RootPaths>
	<DialogueEvents/>
	<StreamedFiles/>
	<MediaFilesNotInAnyBank/>
	<SoundBanks>
		<SoundBank Id="473983015" Language="SFX">
			<ObjectPath>\SoundBanks\Default Work Unit\WindBlast</ObjectPath>
			<ShortName>WindBlast</ShortName>
			<Path>WindBlast.bnk</Path>
			<IncludedEvents>
				<Event Id="473983015" Name="WindBlast" ObjectPath="\Events\Default Work Unit\WindBlast"/>
			</IncludedEvents>
			<IncludedMemoryFiles>
				<File Id="938243536" Language="SFX">
					<ShortName>WIND_Gusts_PE03_17_01.wav</ShortName>
					<Path>SFX\WIND_Gusts_PE03_17_01_9E69E797.wem</Path>
				</File>
			</IncludedMemoryFiles>
		</SoundBank>
		<SoundBank Id="1355168291" Language="SFX">
			<ObjectPath>Init</ObjectPath>
			<ShortName>Init</ShortName>
			<Path>Init.bnk</Path>
		</SoundBank>
	</SoundBanks>
</SoundBanksInfo>
